getman/__init__.py
getman/base.py
getman/client.py
getman/constant.py
getman/files.py
getman/http.py
getman/mock.py
getman/settings.py
getman/utils.py
getman/version.py
getman/manager/__init__.py
getman/manager/dict.py
getman/manager/platform.py
getman/manager/queue.py
getman/manager/sessions.py
getman/manager/browser/__init__.py
getman/manager/browser/base.py
getman/manager/browser/browser.py
getman/manager/browser/constant.py
getman/manager/browser/firefox.py
getman/manager/browser/manager.py
getman/models/__init__.py
getman/models/struct.py
getman/utils/__init__.py
getman/utils/decorators.py
getman-1.0.0.dist-info/LICENSE
getman-1.0.0.dist-info/METADATA
getman-1.0.0.dist-info/WHEEL
getman-1.0.0.dist-info/top_level.txt
getman-1.0.0.dist-info/RECORD
