Metadata-Version: 2.1
Name: getman
Version: 1.0.0
Summary: GetMan is a versatile tool inspired by Postman that simplifies the process of testing and exploring APIs.
Home-page: https://github.com/vnpnh/GetMan
Author: vnpnh
Author-email: no@email.com
License: MIT
Keywords: API testing,API exploration,HTTP requests,API endpoints,request headers,query parameters,request bodies,API management,Postman alternative,RESTful APIs,testing tool,debugging tool,development tools,API client,API interaction.
Classifier: License :: OSI Approved :: MIT License
Classifier: Operating System :: OS Independent
Classifier: Programming Language :: Python :: 3
Classifier: Programming Language :: Python :: 3.11
Classifier: Programming Language :: Python :: 3.12
Requires-Python: >=3.11
License-File: LICENSE
Requires-Dist: requests>=2.32.3
Requires-Dist: rich>=13.8.0
Requires-Dist: browser-cookie3>=0.19.1
